airflow/providers/vertica/__init__.py
airflow/providers/vertica/get_provider_info.py
airflow/providers/vertica/hooks/__init__.py
airflow/providers/vertica/hooks/vertica.py
apache_airflow_providers_vertica-4.2.1.dist-info/entry_points.txt
apache_airflow_providers_vertica-4.2.1.dist-info/licenses/LICENSE
apache_airflow_providers_vertica-4.2.1.dist-info/licenses/NOTICE
apache_airflow_providers_vertica-4.2.1.dist-info/WHEEL
apache_airflow_providers_vertica-4.2.1.dist-info/METADATA
apache_airflow_providers_vertica-4.2.1.dist-info/RECORD
